tilores/__init__.py
tilores/conversion.py
tilores/helpers.py
tilores/record_insights.py
tilores/tilores_api.py
tilores_sdk-0.4.0.dist-info/LICENSE
tilores_sdk-0.4.0.dist-info/METADATA
tilores_sdk-0.4.0.dist-info/WHEEL
tilores_sdk-0.4.0.dist-info/top_level.txt
tilores_sdk-0.4.0.dist-info/RECORD
