Metadata-Version: 2.1
Name: tilores-sdk
Version: 0.4.0
Summary: This is the offical SDK to develop with the Tilores entity resolution database.
Author-email: Lukas Rieder <lukas@parlant.co>, Stefan Berkner <stefan.berkner@tilores.io>
License: MIT License
Project-URL: Homepage, https://github.com/tilotech/python-tilores-sdk
Project-URL: Issues, https://github.com/tilotech/python-tilores-sdk/issues
Keywords: entity-resolution,tilores,graph-rag
Classifier: Programming Language :: Python :: 3
Classifier: License :: OSI Approved :: MIT License
Classifier: Operating System :: OS Independent
Requires-Python: >=3.8
License-File: LICENSE
Requires-Dist: requests>=2.32.3
Requires-Dist: graphql-core>=3.2.3
Requires-Dist: graphql-query>=1.4.0
Provides-Extra: test
Requires-Dist: pytest==8.3.2; extra == "test"
